dc.py-0.0.1.dist-info/DESCRIPTION.rst
dc.py-0.0.1.dist-info/METADATA
dc.py-0.0.1.dist-info/metadata.json
dc.py-0.0.1.dist-info/RECORD
dc.py-0.0.1.dist-info/top_level.txt
dc.py-0.0.1.dist-info/WHEEL
dcpy/author.py
dcpy/bot.py
dcpy/button_interaction.py
dcpy/channel.py
dcpy/client.py
dcpy/component_builder.py
dcpy/events.py
dcpy/helper.py
dcpy/interaction.py
dcpy/message.py
dcpy/message_embed.py
dcpy/user.py
dcpy/__init__.py
