Metadata-Version: 2.0
Name: dc.py
Version: 0.0.1
Summary: Python API Wrapper for Discord.
Home-page: https://github.com/LetsPlayNik/dc.py
Author: Niklas
Author-email: UNKNOWN
License: MIT
Platform: UNKNOWN
